[1,["f5osGG8RtAY4x3vqf9dacT","4bZ/6dVTJPv4FO2IbAasN7","e6cydtu5JI6Zn2YrlsimsH","82X5QvtVBNk6/T82Osx3gl"],["_textureSetter"],["cc.SpriteFrame"],0,[[[{"name":"boom_00004","rect":[21,0,249,165],"offset":[-4.5,1.5],"originalSize":[300,168],"capInsets":[0,0,0,0]}],[0],0,[0],[0],[0]],[[{"name":"boom_00002","rect":[0,0,300,168],"offset":[0,0],"originalSize":[300,168],"capInsets":[0,0,0,0]}],[0],0,[0],[0],[1]],[[{"name":"boom_00001","rect":[0,0,300,168],"offset":[0,0],"originalSize":[300,168],"capInsets":[0,0,0,0]}],[0],0,[0],[0],[2]],[[{"name":"boom_00003","rect":[23,0,244,166],"offset":[-5,1],"originalSize":[300,168],"capInsets":[0,0,0,0]}],[0],0,[0],[0],[3]]]]